stocktrim_mcp_server/__init__.py
stocktrim_mcp_server/context.py
stocktrim_mcp_server/dependencies.py
stocktrim_mcp_server/logging_config.py
stocktrim_mcp_server/observability.py
stocktrim_mcp_server/server.py
stocktrim_mcp_server/unpack.py
stocktrim_mcp_server/utils.py
stocktrim_mcp_server/prompts/__init__.py
stocktrim_mcp_server/prompts/workflows.py
stocktrim_mcp_server/resources/__init__.py
stocktrim_mcp_server/resources/foundation.py
stocktrim_mcp_server/resources/reports.py
stocktrim_mcp_server/services/__init__.py
stocktrim_mcp_server/services/base.py
stocktrim_mcp_server/services/customers.py
stocktrim_mcp_server/services/inventory.py
stocktrim_mcp_server/services/locations.py
stocktrim_mcp_server/services/products.py
stocktrim_mcp_server/services/purchase_orders.py
stocktrim_mcp_server/services/sales_orders.py
stocktrim_mcp_server/services/suppliers.py
stocktrim_mcp_server/templates/__init__.py
stocktrim_mcp_server/templates/forecast_complete.md
stocktrim_mcp_server/templates/forecast_failed.md
stocktrim_mcp_server/templates/forecast_query_empty.md
stocktrim_mcp_server/templates/forecast_query_failed.md
stocktrim_mcp_server/templates/forecast_timeout.md
stocktrim_mcp_server/templates/forecast_triggered.md
stocktrim_mcp_server/tools/__init__.py
stocktrim_mcp_server/tools/customers.py
stocktrim_mcp_server/tools/inventory.py
stocktrim_mcp_server/tools/products.py
stocktrim_mcp_server/tools/foundation/__init__.py
stocktrim_mcp_server/tools/foundation/customers.py
stocktrim_mcp_server/tools/foundation/inventory.py
stocktrim_mcp_server/tools/foundation/locations.py
stocktrim_mcp_server/tools/foundation/products.py
stocktrim_mcp_server/tools/foundation/purchase_orders.py
stocktrim_mcp_server/tools/foundation/sales_orders.py
stocktrim_mcp_server/tools/foundation/suppliers.py
stocktrim_mcp_server/tools/workflows/__init__.py
stocktrim_mcp_server/tools/workflows/forecast_management.py
stocktrim_mcp_server/tools/workflows/product_management.py
stocktrim_mcp_server-0.15.0.dist-info/METADATA
stocktrim_mcp_server-0.15.0.dist-info/WHEEL
stocktrim_mcp_server-0.15.0.dist-info/entry_points.txt
stocktrim_mcp_server-0.15.0.dist-info/RECORD
