Metadata-Version: 2.4
Name: stocktrim-mcp-server
Version: 0.15.0
Summary: Model Context Protocol (MCP) server for StockTrim Inventory Management API
Author-email: Doug Borg <dougborg@dougborg.org>
Maintainer-email: Doug Borg <dougborg@dougborg.org>
License: MIT
Keywords: api-client,mcp,model-context-protocol,stocktrim
Classifier: Development Status :: 3 - Alpha
Classifier: Intended Audience :: Developers
Classifier: License :: OSI Approved :: MIT License
Classifier: Operating System :: OS Independent
Classifier: Programming Language :: Python :: 3
Classifier: Programming Language :: Python :: 3.11
Classifier: Programming Language :: Python :: 3.12
Classifier: Programming Language :: Python :: 3.13
Classifier: Topic :: Software Development :: Libraries :: Python Modules
Classifier: Typing :: Typed
Requires-Python: <3.14,>=3.11
Requires-Dist: fastmcp>=0.3.0
Requires-Dist: python-dotenv>=1.0.0
Requires-Dist: stocktrim-openapi-client
Requires-Dist: structlog>=24.1.0
